<odoo>
    <data noupdate="1">

        <!-- 1. TEXTO CORTO -->
        <record id="question_type_text_short" model="survey.question.type">
            <field name="cod_question_type">text_short</field>
            <field name="nam_question_type">Texto corto</field>
            <field name="typ_data">string</field>
            <field name="nam_ui_component">InputText</field>
            <field name="flg_supports_multiple" eval="False"/>
            <field name="flg_supports_media" eval="False"/>
            <field name="flg_supports_gps" eval="False"/>
            <field name="flg_supports_score" eval="False"/>
            <field name="flg_supports_offline" eval="True"/>
            <field name="activo" eval="True"/>
        </record>

        <!-- 2. TEXTO LARGO -->
        <record id="question_type_text_long" model="survey.question.type">
            <field name="cod_question_type">text_long</field>
            <field name="nam_question_type">Texto largo</field>
            <field name="typ_data">string</field>
            <field name="nam_ui_component">Textarea</field>
            <field name="flg_supports_multiple" eval="False"/>
            <field name="flg_supports_media" eval="False"/>
            <field name="flg_supports_gps" eval="False"/>
            <field name="flg_supports_score" eval="False"/>
            <field name="flg_supports_offline" eval="True"/>
            <field name="activo" eval="True"/>
        </record>

        <!-- 3. NUMERO -->
        <record id="question_type_number" model="survey.question.type">
            <field name="cod_question_type">number</field>
            <field name="nam_question_type">Número</field>
            <field name="typ_data">number</field>
            <field name="nam_ui_component">InputNumber</field>
            <field name="flg_supports_multiple" eval="False"/>
            <field name="flg_supports_media" eval="False"/>
            <field name="flg_supports_gps" eval="False"/>
            <field name="flg_supports_score" eval="True"/>
            <field name="flg_supports_offline" eval="True"/>
            <field name="activo" eval="True"/>
        </record>

        <!-- 4. FECHA -->
        <record id="question_type_date" model="survey.question.type">
            <field name="cod_question_type">date</field>
            <field name="nam_question_type">Fecha</field>
            <field name="typ_data">date</field>
            <field name="nam_ui_component">DatePicker</field>
            <field name="flg_supports_multiple" eval="False"/>
            <field name="flg_supports_media" eval="False"/>
            <field name="flg_supports_gps" eval="False"/>
            <field name="flg_supports_score" eval="False"/>
            <field name="flg_supports_offline" eval="True"/>
            <field name="activo" eval="True"/>
        </record>

        <!-- 5. FECHA Y HORA -->
        <record id="question_type_datetime" model="survey.question.type">
            <field name="cod_question_type">datetime</field>
            <field name="nam_question_type">Fecha y hora</field>
            <field name="typ_data">datetime</field>
            <field name="nam_ui_component">DateTimePicker</field>
            <field name="flg_supports_multiple" eval="False"/>
            <field name="flg_supports_media" eval="False"/>
            <field name="flg_supports_gps" eval="False"/>
            <field name="flg_supports_score" eval="False"/>
            <field name="flg_supports_offline" eval="True"/>
            <field name="activo" eval="True"/>
        </record>

        <!-- 6. OPCION ÚNICA (RADIO) -->
        <record id="question_type_radio" model="survey.question.type">
            <field name="cod_question_type">radio</field>
            <field name="nam_question_type">Opción única</field>
            <field name="typ_data">string</field>
            <field name="nam_ui_component">RadioGroup</field>
            <field name="flg_supports_multiple" eval="False"/>
            <field name="flg_supports_media" eval="False"/>
            <field name="flg_supports_gps" eval="False"/>
            <field name="flg_supports_score" eval="True"/>
            <field name="flg_supports_offline" eval="True"/>
            <field name="activo" eval="True"/>
        </record>

        <!-- 7. OPCION MULTIPLE (CHECKBOX) -->
        <record id="question_type_checkbox" model="survey.question.type">
            <field name="cod_question_type">checkbox</field>
            <field name="nam_question_type">Opción múltiple</field>
            <field name="typ_data">json</field>
            <field name="nam_ui_component">CheckboxGroup</field>
            <field name="flg_supports_multiple" eval="True"/>
            <field name="flg_supports_media" eval="False"/>
            <field name="flg_supports_gps" eval="False"/>
            <field name="flg_supports_score" eval="True"/>
            <field name="flg_supports_offline" eval="True"/>
            <field name="activo" eval="True"/>
        </record>

        <!-- 8. MATRIZ -->
        <record id="question_type_matrix" model="survey.question.type">
            <field name="cod_question_type">matrix</field>
            <field name="nam_question_type">Matriz</field>
            <field name="typ_data">json</field>
            <field name="nam_ui_component">MatrixGrid</field>
            <field name="flg_supports_multiple" eval="True"/>
            <field name="flg_supports_media" eval="False"/>
            <field name="flg_supports_gps" eval="False"/>
            <field name="flg_supports_score" eval="True"/>
            <field name="flg_supports_offline" eval="True"/>
            <field name="activo" eval="True"/>
        </record>

        <!-- 9. ESCALA -->
        <record id="question_type_scale" model="survey.question.type">
            <field name="cod_question_type">scale</field>
            <field name="nam_question_type">Escala</field>
            <field name="typ_data">number</field>
            <field name="nam_ui_component">ScaleSlider</field>
            <field name="flg_supports_multiple" eval="False"/>
            <field name="flg_supports_media" eval="False"/>
            <field name="flg_supports_gps" eval="False"/>
            <field name="flg_supports_score" eval="True"/>
            <field name="flg_supports_offline" eval="True"/>
            <field name="activo" eval="True"/>
        </record>

        <!-- 10. GRID DE LECTURA -->
        <record id="question_type_reading_grid" model="survey.question.type">
            <field name="cod_question_type">reading_grid</field>
            <field name="nam_question_type">Grid de lectura</field>
            <field name="typ_data">json</field>
            <field name="nam_ui_component">ReadingGrid</field>
            <field name="flg_supports_multiple" eval="True"/>
            <field name="flg_supports_media" eval="False"/>
            <field name="flg_supports_gps" eval="False"/>
            <field name="flg_supports_score" eval="True"/>
            <field name="flg_supports_offline" eval="True"/>
            <field name="activo" eval="True"/>
        </record>

        <!-- 11. GRID MATEMÁTICO -->
        <record id="question_type_math_grid" model="survey.question.type">
            <field name="cod_question_type">math_grid</field>
            <field name="nam_question_type">Grid matemático</field>
            <field name="typ_data">json</field>
            <field name="nam_ui_component">MathGrid</field>
            <field name="flg_supports_multiple" eval="True"/>
            <field name="flg_supports_media" eval="False"/>
            <field name="flg_supports_gps" eval="False"/>
            <field name="flg_supports_score" eval="True"/>
            <field name="flg_supports_offline" eval="True"/>
            <field name="activo" eval="True"/>
        </record>

    </data>
</odoo>
